src/__init__.py
src/sfilter/__init__.py
src/sfilter/main.py
tests/__init__.py
tests/sfilter/__init__.py
tests/sfilter/integration/__init__.py
tests/sfilter/integration/test_without_setup_cfg.py
tests/sfilter/unit/__init__.py
tests/sfilter/unit/fixtures.py
tests/sfilter/unit/test_arguments_handler.py
tests/sfilter/unit/test_black.py
tests/sfilter/unit/test_flake8.py
tests/sfilter/unit/test_isort.py
tests/sfilter/unit/test_radon.py
tests/sfilter/unit/test_setup_handler.py
sfilter-0.1.1.dist-info/LICENSE
sfilter-0.1.1.dist-info/METADATA
sfilter-0.1.1.dist-info/WHEEL
sfilter-0.1.1.dist-info/entry_points.txt
sfilter-0.1.1.dist-info/top_level.txt
sfilter-0.1.1.dist-info/RECORD
