Metadata-Version: 2.1
Name: sfilter
Version: 0.1.1
Summary: Tool for filtering out stinky/smelling code
Home-page: https://github.com/alex-d-bondarev/sfilter
Author: Sasha Bondarev (Oleksandr)
Author-email: alex.d.bondarev@gmail.com
License: MIT
Platform: UNKNOWN
Classifier: Development Status :: 2 - Pre-Alpha
Classifier: Intended Audience :: Developers
Classifier: Programming Language :: Python :: 3
Classifier: Programming Language :: Python :: 3.7
Classifier: Programming Language :: Python :: 3.8
Classifier: Programming Language :: Python :: 3.9
Classifier: License :: OSI Approved :: MIT License
Classifier: Operating System :: OS Independent
Classifier: Topic :: Software Development :: Quality Assurance
Requires-Python: >=3.7
License-File: LICENSE
Requires-Dist: black (==21.7b0)
Requires-Dist: click (==8.0.3)
Requires-Dist: ConfigUpdater (==3.0.1)
Requires-Dist: flake8 (==3.9.2)
Requires-Dist: isort (==5.9.2)
Requires-Dist: radon (==4.1.0)
